valis/__init__.py
valis-0.1.dist-info/DESCRIPTION.rst
valis-0.1.dist-info/METADATA
valis-0.1.dist-info/RECORD
valis-0.1.dist-info/WHEEL
valis-0.1.dist-info/metadata.json
valis-0.1.dist-info/top_level.txt
