Metadata-Version: 2.0
Name: valis
Version: 0.1
Summary: UNKNOWN
Home-page: https://github.com/VALIS-software/valis-python-client
Author: Salik Syed
Author-email: UNKNOWN
License: UNKNOWN
Platform: UNKNOWN
Requires-Dist: requests
